atro_docs/__init__.py
atro_docs/__main__.py
atro_docs/constants.py
atro_docs/gen_docs.py
atro_docs/git_helpers.py
atro_docs/inputs.py
atro_docs/mkdocs_helpers.py
atro_docs/repo.py
atro_docs/temp_dir.py
atro_docs/webhook.py
atro_docs-0.0.6.dist-info/METADATA
atro_docs-0.0.6.dist-info/WHEEL
atro_docs-0.0.6.dist-info/RECORD
