Metadata-Version: 2.1
Name: atro-docs
Version: 0.0.6
Summary: 
Author: atropos
Author-email: sv7n@pm.me
Requires-Python: >=3.8,<4.0
Classifier: Programming Language :: Python :: 3
Classifier: Programming Language :: Python :: 3.8
Classifier: Programming Language :: Python :: 3.9
Classifier: Programming Language :: Python :: 3.10
Classifier: Programming Language :: Python :: 3.11
Requires-Dist: cleo
Requires-Dist: fastapi
Requires-Dist: mkdocs
Requires-Dist: mkdocs-include-markdown-plugin
Requires-Dist: mkdocs-material
Requires-Dist: mkdocs-multirepo-plugin
Requires-Dist: mkdocstrings
Requires-Dist: mkdocstrings-python
Requires-Dist: pydantic (>=2.1.1,<3.0.0)
Requires-Dist: sh
Requires-Dist: uvicorn
